llmate/__init__.py
llmate/cli.py
llmate-0.1.0.dist-info/METADATA
llmate-0.1.0.dist-info/WHEEL
llmate-0.1.0.dist-info/entry_points.txt
llmate-0.1.0.dist-info/top_level.txt
llmate-0.1.0.dist-info/RECORD
