Metadata-Version: 2.1
Name: llmate
Version: 0.1.0
Author-email: Stephan Fitzpatrick <knowsuchagency@gmail.com>
License: Apache-2.0
Requires-Python: >=3.10
Requires-Dist: textual (>=0.24.1)
Requires-Dist: openai (>=0.27.6)
